<!-- vertical icon menu -->

<theme>
  <formatVersion>4</formatVersion>
    <include>./common.xml</include>
  <feature supported="carousel">
  <view name="system">
   <carousel name="systemcarousel">
      <type>vertical</type>
      <pos>-0.05 0.3</pos>
      <size>1 1</size>
      <color>ffffff00</color>
      <logoScale>1</logoScale>
      <logoSize>0.3 1</logoSize>
      <maxLogoCount>1</maxLogoCount>
		<logoAlignment>right</logoAlignment>
      <defaultTransition>instant</defaultTransition>		
    </carousel>
 
	  	<image name="logo">
		<path>./../assets/logos/logo/$system.png</path>
	</image>
    
    <text name="systemInfo">
         <pos>0.032 0.868</pos>
         <alignment>left</alignment>
   </text>
	  
   <helpsystem name="help">    
         <pos>0.032 0.940</pos>      
   </helpsystem>

	  </view>
  </feature>  
</theme>
